{"data":{"user":{"name":"Richard S. Franklin","bio":"ML Engineer and Researcher","avatarUrl":"https://avatars.githubusercontent.com/u/15136466?u=1305585b1a6df0b4f4d16434ca634458a7662246&v=4","location":null,"pinnedItems":{"totalCount":5,"edges":[{"node":{"name":"graphbook","description":"The framework for AI-driven data pipelines. Build interactive, highly efficient data pipelines with PyTorch. ⭐ Leave a star to support us!","forkCount":1,"stargazers":{"totalCount":24},"url":"https://github.com/graphbookai/graphbook","id":"R_kgDOLvs3Sw","diskUsage":1366,"primaryLanguage":{"name":"TypeScript","color":"#3178c6"}}},{"node":{"name":"wow-fishing-bot","description":"A fishing bot for World of Warcraft that uses template matching from OpenCV. No GPU","forkCount":25,"stargazers":{"totalCount":58},"url":"https://github.com/rsamf/wow-fishing-bot","id":"MDEwOlJlcG9zaXRvcnkyMTg4NDQxNzY=","diskUsage":57249,"primaryLanguage":{"name":"Python","color":"#3572A5"}}},{"node":{"name":"text-guided-mixup","description":"PyTorch implementation of paper \"Text-Guided Mixup Towards Long-Tailed Image Categorization\" (BMVC 2024)","forkCount":0,"stargazers":{"totalCount":4},"url":"https://github.com/rsamf/text-guided-mixup","id":"R_kgDOJNBsQQ","diskUsage":17876,"primaryLanguage":{"name":"Python","color":"#3572A5"}}},{"node":{"name":"limelight","description":"DJ Spotify collaboration iOS app","forkCount":1,"stargazers":{"totalCount":2},"url":"https://github.com/rsamf/limelight","id":"MDEwOlJlcG9zaXRvcnkxNDI2NDczNjA=","diskUsage":1773,"primaryLanguage":{"name":"JavaScript","color":"#f1e05a"}}},{"node":{"name":"i-gotta-go","description":"Restroom reviews and locator app. Winner of sponsor prize from Stanford Tree Hacks 2018.","forkCount":0,"stargazers":{"totalCount":1},"url":"https://github.com/rsamf/i-gotta-go","id":"MDEwOlJlcG9zaXRvcnkxMjE4MzEwNTQ=","diskUsage":859,"primaryLanguage":{"name":"JavaScript","color":"#f1e05a"}}}]}}}}